[
  {
    "round": 1,
    "teacherReplyText": "针对学生对\"变量与函数关系\"理解不透的问题，我为您设计一个**\"函数关系探秘——从变化中发现规律\"**的探究性教学活动：\n\n## 1. 活动概要\n- **活动名称**：函数关系探秘——从变化中发现规律\n- **适用年级**：八年级上学期（函数概念入门阶段）\n- **对应课标**：《义务教育数学课程标准（2022年版）》\"数与代数\"领域——函数概念、变量与常量、函数关系的识别\n- **建议课时**：1课时（45分钟）\n- **课型定位**：概念建构课\n\n## 2. 活动目标\n\n| 目标维度 | 具体内容 |\n|---------|---------|\n| **知识技能** | 能区分常量与变量，理解\"一个变量随另一个变量的变化而变化\"的对应关系，能用三种方式（表格、解析式、图像）表示简单函数关系 |\n| **过程方法** | 经历\"观察变化→提出猜想→验证规律→符号表达\"的探究过程，发展数据分析与合作交流能力 |\n| **素养发展** | 发展抽象能力与模型观念，体会从具体到抽象、从特殊到一般的数学思想 |\n\n## 3. 活动准备\n\n**教具与学具**：\n- 弹簧秤与钩码套装（每组一套）\n- 记录单（含表格模板）\n- 坐标纸与直尺\n- GeoGebra课件（备用）\n\n**前置知识**：已学过代数式、方程，能理解\"未知数\"的概念\n\n**分组**：4-5人异质分组（含记录员、操作员、汇报员、质疑员等角色）\n\n## 4. 活动流程\n\n### 环节一：情境导入——制造认知冲突（6分钟）\n\n**问题提出**：\n> 老师网购了一批苹果，每斤6元。请思考：\n> - 买2斤要付多少钱？买5斤呢？买x斤呢？\n> - 在这个问题中，哪些量在变化？哪些量始终不变？\n> - 如果涨价到每斤8元，上述关系还成立吗？\n\n**学生活动**：独立思考2分钟，小组讨论1分钟\n\n**预设生成**：\n- 学生易混淆\"单价x重量=总价\"中的变量关系\n- 引导学生发现：**重量变化 → 总价随之变化，但单价始终不变**\n\n### 环节二：探究实践——多维度体验变量关系（18分钟）\n\n#### 【任务1】弹簧实验：探索长度与质量的关系（12分钟）\n\n**操作指导**：\n1. 记录弹簧原长（不挂钩码时）\n2. 依次挂上1个、2个、3个、4个、5个钩码，记录弹簧长度\n3. 填写表格：\n\n| 钩码数量n（个） | 0 | 1 | 2 | 3 | 4 | 5 |\n|-----------------|---|---|---|---|---|---|\n| 弹簧总长度L（cm） |   |   |   |   |   |   |\n\n**探究问题链**：\n1. 哪些量在变化？它们是如何变化的？（变量识别）\n2. 钩码数量与弹簧长度有什么关系？（对应关系初步感知）\n3. 如果挂10个钩码，弹簧会有多长？（预测与验证）\n4. 能否用数学式子表示这种关系？（符号化表达）\n\n**分层设计**：\n- 基础层：完成表格填写，描述变化趋势\n- 提高层：尝试写出L与n的代数关系式\n- 挑战层：探究\"弹簧为什么会伸长\"，联系物理胡克定律\n\n**教师巡视要点**：\n- 观察学生是否能区分\"变量\"与\"常量\"\n- 记录典型错误（如混淆原长与伸长量）\n- 为后续交流准备素材\n\n#### 【任务2】\"函数关系诊断\"——辨析真假函数（6分钟）\n\n**小组讨论**：判断以下情境是否存在函数关系，说明理由\n\n| 情境1 | 日期 | 6.1 | 6.2 | 6.3 | 6.5 |\n|-------|------|-----|-----|-----|-----|\n|       | 气温 | 28° | 29° | 28° | 30° |\n\n| 情境2 | 同学编号 | 1 | 2 | 3 | 4 |\n|-------|----------|---|---|---|---|\n|       | 身高(cm) | 155 | 160 | 158 | 162 |\n\n| 情境3 | x | 1 | 2 | 3 | 2 |\n|-------|---|---|---|---|---|\n|       | y | 3 | 5 | 7 | 5 |\n\n**关键提问**：\n- 对于同一个x值，y值是否唯一确定？\n- 函数的本质特征是什么？\n\n### 环节三：交流建构——概念形成与规范（10分钟）\n\n**小组汇报**（每组3分钟）：\n- 展示实验数据与发现\n- 争议性问题全班讨论\n\n**数学概念正式引入**：\n- **变量**：在变化过程中数值发生变化的量（如钩码数量n、弹簧长度L）\n- **常量**：在变化过程中数值始终不变的量（如弹簧原长、钩码质量）\n- **函数**：在一个变化过程中，如果有两个变量x与y，对于x的每一个确定的值，y都有唯一确定的值与之对应，则称y是x的函数\n\n**关键强调**（板书呈现）：\n```\n函数关系的本质特征：\n① 存在两个变量\n② 一个变量的值确定 → 另一个变量的值随之确定（对应关系）\n③ 对应具有唯一性\n```\n\n**常见错误纠正**：\n- 错误认识：\"y随x增大而增大才是函数\" → 反例：y随x增大而减小（如路程=速度×时间中，固定路程时时间与速度的关系）\n- 错误认识：\"x变了y必须变\" → 反例：常函数（如y=5）\n\n### 环节四：应用迁移——变式巩固（8分钟）\n\n**练习1：识别函数关系（基础）**\n\n| x | 1 | 2 | 3 | 4 |\n|---|---|---|---|---|\n| y | 2 | 4 | 6 | 8 |\n\n| x | 1 | 2 | 2 | 4 |\n|---|---|---|---|---|\n| y | 3 | 4 | 5 | 6 |\n\n**练习2：情境应用（提高）**\n小明家到学校的距离是1200米，他以每分钟80米的速度步行上学。\n- 指出问题中的变量与常量\n- 用式子表示剩余路程s与时间t的关系\n- 这个关系中，谁是自变量？谁是因变量？\n\n**练习3：开放探究（拓展）**\n设计一个生活中的问题情境，要求：\n- 包含两个变量\n- 体现明确的对应关系\n- 能用表格、式子、图像三种方式表示\n\n### 环节五：总结反思——知识结构化（3分钟）\n\n**思维导图梳理**：\n```\n函数概念入门\n├── 变量与常量\n│   ├── 变量：数值变化的量（x, y...）\n│   └── 常量：数值不变的量（如k, b...）\n├── 函数本质\n│   ├── 两个变量\n│   ├── 对应关系\n│   └── 唯一性（一个x对应唯一y）\n└── 表示方法\n    ├── 表格法\n    ├── 解析式法\n    └── 图像法\n```\n\n**元认知提示**：\n- \"今天我最困惑的地方是______\"\n- \"变量与常量的区别关键在于______\"\n- \"判断函数关系，我重点要看______\"\n\n## 5. 差异化设计\n\n| 学生层次 | 支持策略 | 具体措施 |\n|---------|---------|---------|\n| **基础薄弱** | 脚手架支持 | 提供\"变量识别检查清单\"；使用具体数值替代符号；小组内配备小助手角色 |\n| **中等学生** | 适度挑战 | 变式练习梯度设计，鼓励多种方法验证 |\n| **学有余力** | 拓展延伸 | 探究\"多对一\"与\"一对多\"的区别；研究分段函数；设计跨学科项目（如物理中的运动学公式） |\n\n## 6. 评价设计\n\n**表现性评价量表**：\n\n| 评价维度 | 优秀(4分) | 良好(3分) | 合格(2分) | 需努力(1分) |\n|---------|----------|----------|----------|-----------|\n| **变量识别** | 能准确区分变量与常量 | 能识别但偶有混淆 | 需要提示才能区分 | 基本无法区分 |\n| **函数理解** | 能用自己的语言精准描述对应关系 | 能描述但不够完整 | 仅能举出例子 | 理解存在明显偏差 |\n| **合作探究** | 积极参与实验，贡献有价值的发现 | 参与实验，能完成分工任务 | 参与度一般 | 参与度低 |\n| **数学表达** | 能用三种方式清晰表达函数关系 | 能用两种方式表达 | 仅能表达一种 | 表达混乱 |\n\n**关键诊断提问**：\n1. \"如果x=3时，y可以等于4也可以等于5，这是函数关系吗？为什么？\"\n2. \"在弹簧实验中，弹簧原长是变量还是常量？\"\n3. \"函数关系一定是一个增大另一个也增大吗？请举例说明\"\n\n## 7. 设计说明\n\n**理论依据**：\n- **APOS理论**：活动(Action)→过程(Process)→对象(Object)→图式(Schema)，本设计从具体操作（弹簧实验）逐步抽象到函数概念\n- **变式教学理论**：通过\"真假函数诊断\"辨析正例与反例，突出概念本质属性\n- **多元表征理论**：表格、代数式、图像三种表示方式促进深度理解\n\n**常见生成问题应对**：\n| 问题 | 应对策略 |\n|------|---------|\n| 学生混淆\"变量\"与\"未知数\" | 强调：未知数是方程中求解的目标（确定但未知），变量是变化过程中的量（随情境改变） |\n| 学生认为y必须随x增大而增大 | 反例辨析：如固定路程时，速度越大时间越短；介绍常函数、减函数 |\n| 学生不理解\"唯一对应\" | 结合实际情境：一个学生只能对应一个学号；身高对应日期不是函数 |\n\n**中考衔接**：该活动对应中考函数综合题中的基础考点——函数概念辨析、自变量取值范围、函数图像识别\n\n---\n\n**实施建议**：\n1. 弹簧实验是本活动的核心，建议提前试做，确保数据规律明显\n2. 学生汇报环节要给予充足时间暴露思维，特别是错误思路\n3. 如果课时紧张，可将\"真假函数诊断\"作为课后作业并在下节课反馈\n\n这个活动设计通过**动手操作+认知冲突+合作探究**，帮助学生从具体经验中建构函数概念，有效化解\"变量-函数\"理解的常见误区。如需调整难度或补充其他活动形式，我可以进一步优化。",
    "studentRawOutput": "FOLLOW_UP: 请基于上述教学设计开始实际的教学问答，扮演教师角色执行\"情境导入\"环节，直接向学生（我）提出那个关于买苹果的问题，我们来进行师生互动。",
    "parsedDecision": {
      "type": "follow_up",
      "question": "请基于上述教学设计开始实际的教学问答，扮演教师角色执行\"情境导入\"环节，直接向学生（我）提出那个关于买苹果的问题，我们来进行师生互动。"
    }
  }
]
