[
  {
    "round": 1,
    "teacherReplyText": "## 装置选择核心依据（一句话记住）\n\n**看反应物状态和条件 → 选发生装置；看气体密度和溶解性 → 选收集装置**\n\n---\n\n### 一、发生装置的选择\n\n| 类型 | 适用场景 | 典型实例 |\n|------|----------|----------|\n| **固固加热型** | 固体反应物 + 需要加热 | 加热KMnO₄或KClO₃制O₂ |\n| **固液常温型** | 固体+液体 + 不需加热 | H₂O₂溶液+MnO₂制O₂；石灰石+稀盐酸制CO₂ |\n\n**关键记忆点**：\n- 用试管加热固体时，**试管口要略向下倾斜**（防止冷凝水倒流炸裂试管）\n- 用长颈漏斗时，**下端必须液封**（防止气体从漏斗逸出）\n\n---\n\n### 二、收集装置的选择\n\n| 收集方法 | 选择依据 | 典型气体 |\n|----------|----------|----------|\n| **排水法** | 气体难溶于水且不与水反应 | O₂、H₂（收集的气体较纯净） |\n| **向上排空气法** | 气体密度 > 空气 | CO₂、O₂（相对分子质量 > 29） |\n| **向下排空气法** | 气体密度 < 空气 | H₂（相对分子质量 < 29） |\n\n---\n\n### 三、口诀总结\n\n> **\"固加热，管口下；液常温，漏斗封；密度定上下，溶水用排水\"**\n\n这就是装置选择的完整逻辑链。有什么具体气体的制备方案想了解吗？",
    "studentRawOutput": "FOLLOW_UP: 能否以实验室制取二氧化碳为例，具体说明如何选择发生装置和收集装置，以及组装时有哪些关键注意事项？",
    "parsedDecision": {
      "type": "follow_up",
      "question": "能否以实验室制取二氧化碳为例，具体说明如何选择发生装置和收集装置，以及组装时有哪些关键注意事项？"
    }
  },
  {
    "round": 2,
    "teacherReplyText": "## 实验室制取二氧化碳：装置选择与注意事项\n\n### 2. 原理剖析\n\n**化学方程式**：\n$$\\ce{CaCO3 + 2HCl -> CaCl2 + H2O + CO2 ^}$$\n\n**反应物状态分析**：\n- 石灰石（固体）+ 稀盐酸（液体）\n- **反应条件**：常温（不需加热）\n- **结论**：选择 **固液常温型** 发生装置\n\n**气体性质梳理**：\n- **密度**：$\\ce{CO2}$ 相对分子质量 = 44 > 29，**密度比空气大** → 选用**向上排空气法**\n- **溶解性**：能溶于水且与水反应（$\\ce{CO2 + H2O -> H2CO3}$）→ **不能用排水法**\n\n---\n\n### 3. 装置选择逻辑图\n\n```\n发生装置：固液常温型（锥形瓶+长颈漏斗/分液漏斗）\n         ↓\n收集装置：向上排空气法（导管伸入集气瓶底部）\n```\n\n---\n\n### 4. 关键注意事项（中考高频考点）\n\n| 注意事项 | 原因说明 | 错误后果 |\n|----------|----------|----------|\n| **长颈漏斗下端必须液封** | 防止气体从漏斗逸出 | 收集不到气体或收集很慢 |\n| **导管伸入集气瓶底部** | 密度大的气体下沉，将空气向上排出 | 收集的CO₂混有空气，不纯 |\n| **先检查装置气密性** | 确保装置不漏气 | 气体泄漏，实验失败 |\n| **不能用稀硫酸** | 生成$\\ce{CaSO4}$微溶，覆盖在石灰石表面阻止反应继续进行 | 反应很快停止 |\n| **不能用浓盐酸** | 浓盐酸有挥发性，导致CO₂混有HCl气体 | 气体不纯，影响后续检验 |\n\n---\n\n### 5. 快速检验方法\n\n将燃着的木条放在**集气瓶口**，若火焰熄灭，证明已收集满。\n\n**原理**：CO₂不燃烧也不支持燃烧，密度比空气大，聚集在瓶口。\n\n---\n\n还有哪个细节想深入了解？比如**气密性检查的具体操作**或**装置改进方案**？",
    "studentRawOutput": "DONE",
    "parsedDecision": {
      "type": "done"
    }
  }
]
